README.md
setup.cfg
setup.py
pycarbon/__init__.py
pycarbon/configuration.py
pycarbon.egg-info/PKG-INFO
pycarbon.egg-info/SOURCES.txt
pycarbon.egg-info/dependency_links.txt
pycarbon.egg-info/requires.txt
pycarbon.egg-info/top_level.txt
pycarbon/tests/__init__.py
pycarbon/tests/test_env_vars.py
pycarbon/tests/test_loading.py