Metadata-Version: 1.1
Name: pycarbon
Version: 1.0.7
Summary: A python module for managing YAML config files across multiple environments and files.
Home-page: https://github.com/443labs/pycarbon
Author: Mark Belles
Author-email: markbelles@gmail.com
License: MIT
Download-URL: https://github.com/443labs/pycarbon/archive/1.0.7.tar.gz
Keywords: config,configuration,files,yaml,yml
Platform: UNKNOWN
